yatoro
