Metadata-Version: 2.1
Name: yatoro
Version: 0.0.2
Summary: CHELTI
Home-page: 
Author: Dimasik
Author-email: drobyshevskiydk@gmail.com
License: MIT
Keywords: test
Classifier: Development Status :: 5 - Production/Stable
Classifier: Intended Audience :: Education
Classifier: Operating System :: Microsoft :: Windows :: Windows 10
Classifier: License :: OSI Approved :: MIT License
Classifier: Programming Language :: Python :: 3
License-File: LICENSE.txt
